autoconvo/__init__.py
autoconvo/convo.py
autoconvo-0.0.6.dist-info/LICENSE
autoconvo-0.0.6.dist-info/METADATA
autoconvo-0.0.6.dist-info/WHEEL
autoconvo-0.0.6.dist-info/top_level.txt
autoconvo-0.0.6.dist-info/RECORD
