Metadata-Version: 2.1
Name: autoconvo
Version: 0.0.6
Summary: A package to automatically set up simple convolutional neural networks in PyTorch.
Home-page: https://github.com/franklinscudder/pytorch-convo
Author: Thomas Findlay
Author-email: findlaytel@gmail.com
License: UNKNOWN
Project-URL: Bug Tracker, https://github.com/franklinscudder/pytorch-convo/issues
Platform: UNKNOWN
Classifier: Programming Language :: Python :: 3
Classifier: License :: OSI Approved :: MIT License
Classifier: Operating System :: OS Independent
Classifier: Development Status :: 3 - Alpha
Classifier: Programming Language :: Python :: 3.6
Classifier: Programming Language :: Python :: 3.7
Classifier: Programming Language :: Python :: 3.8
Classifier: Programming Language :: Python :: 3.9
Requires-Python: >=3.6
License-File: LICENSE
Requires-Dist: torch
Requires-Dist: numpy
